openweave-0.3.data/scripts/weave-device-mgr
openweave-0.3.data/platlib/openweave/WeaveBluezMgr.py
openweave-0.3.data/platlib/openweave/WeaveDeviceMgr.py
openweave-0.3.data/platlib/openweave/_WeaveDeviceMgr.so
openweave-0.3.data/platlib/openweave/WeaveBleUtility.py
openweave-0.3.data/platlib/openweave/WdmClient.py
openweave-0.3.data/platlib/openweave/WeaveBleBase.py
openweave-0.3.data/platlib/openweave/WeaveTLV.py
openweave-0.3.data/platlib/openweave/GenericTraitUpdatableDataSink.py
openweave-0.3.data/platlib/openweave/ResourceIdentifier.py
openweave-0.3.data/platlib/openweave/__init__.py
openweave-0.3.data/platlib/openweave/WeaveUtility.py
openweave-0.3.data/platlib/openweave/WeaveCoreBluetoothMgr.py
openweave-0.3.data/platlib/openweave/WeaveStack.py
openweave-0.3.dist-info/METADATA
openweave-0.3.dist-info/RECORD
openweave-0.3.dist-info/LICENSE.txt
openweave-0.3.dist-info/top_level.txt
openweave-0.3.dist-info/WHEEL
