Metadata-Version: 2.1
Name: openweave
Version: 0.3
Summary: Python-base APIs and tools for OpenWeave.
Home-page: https://github.com/openweave/openweave-core
License: Apache
Platform: UNKNOWN
Classifier: Intended Audience :: Developers
Classifier: License :: OSI Approved :: Apache Software License
Classifier: Programming Language :: Python :: 2
Classifier: Programming Language :: Python :: 2.7
Classifier: Programming Language :: Python :: 3
Requires-Python: >=2.7
Requires-Dist: dbus-python
Requires-Dist: pgi
